topazdevsdk/__init__.py
topazdevsdk/colors.py
topazdevsdk/file.py
topazdevsdk/formatting.py
topazdevsdk/report.py
topazdevsdk/time.py
topazdevsdk/version.py
topazdevsdk-1.1.0.dist-info/licenses/LICENSE
topazdevsdk-1.1.0.dist-info/METADATA
topazdevsdk-1.1.0.dist-info/WHEEL
topazdevsdk-1.1.0.dist-info/top_level.txt
topazdevsdk-1.1.0.dist-info/RECORD
