Metadata-Version: 2.4
Name: topazdevsdk
Version: 1.1.0
Summary: TopazDev Python SDK
Author-email: MALLET Maxime <mallet.maxime@topazdev.fr>
License-Expression: MIT
Project-URL: Homepage, https://github.com/azerxim/topazdev-sdk-py
Project-URL: Repository, https://github.com/azerxim/topazdev-sdk-py
Project-URL: Documentation, https://sdk.topazdev.fr/py
Classifier: Programming Language :: Python :: 3
Classifier: Programming Language :: Python :: 3.8
Classifier: Programming Language :: Python :: 3.9
Classifier: Programming Language :: Python :: 3.10
Classifier: Programming Language :: Python :: 3.11
Classifier: Programming Language :: Python :: 3.12
Classifier: Programming Language :: Python :: 3.13
Classifier: Development Status :: 3 - Alpha
Classifier: Intended Audience :: Developers
Classifier: Operating System :: OS Independent
Requires-Python: >=3.8
License-File: LICENSE
Provides-Extra: dev
Requires-Dist: sphinx>=8.1.3; extra == "dev"
Requires-Dist: sphinx-rtd-theme>=3.0.1; extra == "dev"
Requires-Dist: furo>=2024.8.6; extra == "dev"
Requires-Dist: myst-parser>=4.0.0; extra == "dev"
Requires-Dist: pytest; extra == "dev"
Requires-Dist: pytest-sphinx; extra == "dev"
Requires-Dist: pytest-cov; extra == "dev"
Requires-Dist: twine>=1.11.0; extra == "dev"
Requires-Dist: build; extra == "dev"
Requires-Dist: setuptools; extra == "dev"
Requires-Dist: wheel; extra == "dev"
Requires-Dist: sphinx-copybutton; extra == "dev"
Requires-Dist: sphinx-autobuild; extra == "dev"
Requires-Dist: sphinx-autodoc-typehints==1.23.3; extra == "dev"
Requires-Dist: packaging; extra == "dev"
Dynamic: license-file
